dispatch/__init__.py
dispatch/debug.py
dispatch/dispatch.py
gnosis_dispatch-1.0.0.dist-info/METADATA
gnosis_dispatch-1.0.0.dist-info/WHEEL
gnosis_dispatch-1.0.0.dist-info/licenses/LICENSE
gnosis_dispatch-1.0.0.dist-info/RECORD
