Metadata-Version: 2.4
Name: gnosis-dispatch
Version: 1.0.0
Summary: Multiple and Predicative Dispatch
Project-URL: Homepage, https://github.com/DavidMertz/dispatch
Project-URL: Issues, https://github.com/DavidMertz/dispatch/issues
Project-URL: Documentation, https://gnosis-dispatch.readthedocs.io/en/latest/
Project-URL: Repository, https://github.com/DavidMertz/dispatch
Author-email: "David Mertz, Ph.D." <mertz@gnosis.cx>
License-Expression: BSD-2-Clause
License-File: LICENSE
Classifier: Development Status :: 5 - Production/Stable
Classifier: Intended Audience :: Developers
Classifier: Operating System :: OS Independent
Classifier: Programming Language :: Python :: 3
Classifier: Topic :: Software Development :: Libraries
Requires-Python: >=3.13
